{
    "info": {
        "caseField": "",
        "detailField": "",
        "trailField": "",
        "caseNm": "사해행위취소청구사건",
        "courtNm": "대구고법",
        "judmnAdjuDe": "1980.4.30.",
        "caseNo": "78나768",
        "relateLaword": [],
        "qotatPrcdnt": []
    },
    "concerned": {
        "acusr": "",
        "dedat": ""
    },
    "org": {
        "orgJdgmnCourtNm": "",
        "orgJdgmnAdjuDe": "",
        "orgJdgmnCaseNo": ""
    },
    "disposal": {
        "disposalform": "",
        "disposalcontent": []
    },
    "mentionedItems": {
        "rqestObjet": []
    },
    "assrs": {
        "acusrAssrs": [],
        "dedatAssrs": []
    },
    "facts": {
        "bsisFacts": [
            "유일한 부동산매각과 사해행위",
            "사해행위취소로 인한 원상회복의무가 이행불능인 경우 손해배상책임이 있는지 여부"
        ]
    },
    "dcss": {
        "courtDcss": [
            "피고는 소외 1이 이사건 부동산을 처분할 당시에 있어서 이사건 부동산에는 제1순위인 소외 주식회사 대구은행의 근저당권 채권 돈 10000000원 제2순위인 소외 한국출판업협동조합의 근저당권채권 돈 7282139원 그외 제3 내지 6순위까지의 전세권자들의 전세금반환채권 도합 돈 5700000원 제7순위인 피고의 처 소외 8의 근저당권채권 돈 4950000원 제8순위인 피고의 근저당권채권 돈 4950000원등 도합 돈 32932139원의 채권담보를 위한 근저당권 내지 전세권설정등기가 경료되어 있었고 피고는 자신의 채권 돈 9900000원을 건지기 위하여 선순위 피담보채무 도합 돈 23032139원을 부담하고 있는 이사건 부동산을 매수하고 나아가 이사건 부동산에 관한 압류국세 돈 5000000원까지 소외 1을 대위하여 변제함으로써 당시 싯가 돈 25000000원 상당의 이사건 부동산을 도합 돈 37932139원에 취득한 것으로 되었으니 소외 1은 이사건 부동산처분행위는 사해행위로 될 수 없다고 항변하므로 살피건대 가사 이사건 부동산에 관한 피담보채무액이 피고 주장대로이고 소외 1이 이사건 부동산처분대금으로서 위 채무를 변제하였다고 가정 하더라도 이사건 부동산의 처분당시의 싯가가 피고 주장과는 달리 돈 6 내지 7000만원 상당임은 앞서 인정한 바와 같으니 위 사실만가지고서 소외 1의 이사건 부동산처분행위가 채권자인 원고들을 해할 의사에서 나온 것이 아니라고 인정하기에 부족하고 달리 이 점을 인정할 증거없다.",
            "그렇다면 소외 1로부터 이사건 부동산을 취득한 피고에 있어 취득당시 소외 1의 처분행위가 채권자인 원고들을 해한다는 정을 몰랐고 그 모른데 대하여 과실이 없었음을 인정할 자료가 없는 이 사건에 있어서 위 인정의 원고들의 채권범위안에서 소외 1과 피고간의 위 매매계약의 취소를 구하는 원고들의 이사건 청구는 이유있다 할 것이다.",
            "나아가 위 매매계약취소에 따른 원상회복의무로서의 피고명의의 위 가등기 및 본등기의 각 말소등기의무는 앞서 본 바와 같이 이사건 부동산에 관한 피고명의의 등기명의가 1977.8.29.자로 소외 2 앞으로 넘어감으로써 이행불능으로 되었다 할 것이니 피고는 그 이행불능에 갈음하는 배상으로서 원고 1에게 돈 3924000원 원고 2에게 돈 8000000원 원고 3에게 돈 4100000원을 각 지급할 의무가 있다 할 것이다.",
            "따라서 채권액의 범위안에서 위 매매계약의 취소와 원상회복의 무로서의 위 돈의 지급을 구하는 원고들의 이사건 본위적 청구는 모두 이유있으므로 나머지 예비적 청구에 관하여 나아가 판단할 것도 없이 이를 인용할 것인바 원판결은 이와 일부 결론을 달리하여 부당하므로 이를 변경하고 소송비용의 부담에 관하여는 민사소송법 제96조 제89조 제90조 제93조를 가집행의 선고에 관하여는 같은법 제199조를 각 적용하여 주문과 같이 판결한다."
        ]
    },
    "close": {
        "cnclsns": [
            "원판결을 다음과 같이 변경한다."
        ]
    }
}