{
    "info": {
        "caseField": "",
        "detailField": "",
        "trailField": "",
        "caseNm": "국공유지매수인의지위확인",
        "courtNm": "서울고법",
        "judmnAdjuDe": "1990.11.2.",
        "caseNo": "90나27605",
        "relateLaword": [],
        "qotatPrcdnt": []
    },
    "concerned": {
        "acusr": "",
        "dedat": ""
    },
    "org": {
        "orgJdgmnCourtNm": "",
        "orgJdgmnAdjuDe": "",
        "orgJdgmnCaseNo": ""
    },
    "disposal": {
        "disposalform": "",
        "disposalcontent": []
    },
    "mentionedItems": {
        "rqestObjet": []
    },
    "assrs": {
        "acusrAssrs": [],
        "dedatAssrs": []
    },
    "facts": {
        "bsisFacts": [
            "구 국유재산법 의2가 은닉된 국유재산의 자진반환자에게 당해 재산을 매수할 수 있는 권리를 부여하는 취지의 규정인지 여부"
        ]
    },
    "dcss": {
        "courtDcss": [
            "이에 원고는 위에서 인정한 바와 같이 원고가 이 사건 임야에 관한 피고의 소유권을 인정하고 항소를 하지 아니하여 피고에게 이 사건 임야를 자진하여 반환하였으므로 국유재산법 제53조의2에 규정된 은닉재산의 자진반환자 등에 관한 매각특례대상자로서 이 사건 임야를 매수할 매수인의 지위에 있는데도 불구하고 피고는 1989.7.이 사건 임야의 매수를 신청한 원고에 대하여 그 매매를 거절하였으므로 이 사건 임야를 매수할 지위에 있다는 확인을 구한다고 주장하고 있다.",
            "살피건대 이 사건에 있어서와 같이 확정판결에 의하여 국가명의로의 등기를 하여 국유재산을 반환받는 경우에는 등기신청에 있어서 반환자의 협력이 필요 없으므로 그 반환일은 당해 판결이 확정된날로 봄이 상당하다 할 것이고 따라서 이 사건에 있어서는 위 판결이 확정된 1985.12.경이 그 반환일로 된다 할 것인바 위 반환 당시의 국유재산법 제53조의2에는 은닉된 국유재산을 선의로 취득한 후 당해 재산을 국가에 반환한 자에게 동 재산을 매각하는 경우에는 같은 법 제40조의 규정에 불구하고 매각대금을 이자 없이 10년 이하의 기간에 걸쳐 분할납부하게 하거나 매각가격에서 7할을 공제한 잔액을 그 매각대금으로 하여 전액을 일시에 납부하게 할 수 있다고 규정되어 있고 위 조항 소정의 자진반환자에는 이 사건에 있어서와 같이 소송중에 항소기간이 도과하도록 항소를 제기하지 아니하여 국가승소판결을 확정시킨 자도 포함된다 할 것이나 위 조항은 은닉된 국유재산을 자진하여 반환한 자에게 그 국유재산을 매각하는 경우에 그 매각대금 및 대금납입방법에 관한 특례를 규정한 것에 불과하고 은닉된 국유재산을 자진반환한 자에게 그 국유재산으로 매수할 수 있는 권리를 부여한 것이라고 볼 수 없으므로 비록 원고가 국유재산법 제53조의2 소정이 은닉국유재산의 자진반환자로서 그 매각대금 및 대금납입방법에 관한 특례대상자에 해당된다 하더라도 위 사실만으로 바로 그가 이 사건 임야에 관한 매수신청을 하면 그 즉시 위 매수신청에 의하여 당연히 매매계약이 성립된다거나 위 매수신청에 대하여 피고가 응하지 아니하면 아니될 의무가 있다고 볼 수는 없으므로 원고의 이 사건청구는 더 나아가 살펴볼 필요 없이 이유없다 할 것이다.",
            "그렇다면 원고의 이 사건 청구은 이유 없으므로 이를 기각할 것인바 원판결은 이와 결론을 같이하여 정당하므로 원고의 항소를 기각하고 항소비용은 패소자인 원고의 부담으로 하여 주문과 같이 판결한다."
        ]
    },
    "close": {
        "cnclsns": [
            "원고의 항소를 기각한다."
        ]
    }
}