{
    "info": {
        "caseField": "",
        "detailField": "",
        "trailField": "",
        "caseNm": "계약금청구사건",
        "courtNm": "대구고법",
        "judmnAdjuDe": "1981.6.25.",
        "caseNo": "81나158",
        "relateLaword": [],
        "qotatPrcdnt": []
    },
    "concerned": {
        "acusr": "",
        "dedat": ""
    },
    "org": {
        "orgJdgmnCourtNm": "",
        "orgJdgmnAdjuDe": "",
        "orgJdgmnCaseNo": ""
    },
    "disposal": {
        "disposalform": "",
        "disposalcontent": []
    },
    "mentionedItems": {
        "rqestObjet": []
    },
    "assrs": {
        "acusrAssrs": [],
        "dedatAssrs": []
    },
    "facts": {
        "bsisFacts": [
            "대금감액사유가 될 매매목적물의 하자",
            "쌍무계약에 있어 서로 이행기를 도과한 경우의 법률관계"
        ]
    },
    "dcss": {
        "courtDcss": [
            "피고는 원고가 위 계약의 내용에 따른 의무이행이 없어서 이를 이유로 위 매매계약을 해약하였다고 다투므로 살피면",
            "이에 부합하는 당심증인 소외 2의 증언은 이를 쉽사리 믿을 수 없고 달리 이를 인정할 증거가 없고 위 인정사실에 당사자변론의 전취지에 의하면 원고가 위 하자를 이유로 중도금의 지급을 거절하다가 잔대금 지급기일에 이르렀는 사실을 인정할 수 있는 바 이 건과 같은 쌍무계약에 있어서 당사자 쌍방이 소정 이행기일을 각자 도과하였을 경우에 있어서는 그후 그 계약은 이행기일의 약정이 없는 것이 되고 당사자중 일방이 자기의 채무이행을 제공하고 상대방에 대하여 계약의 해제를 최고하여야 하는바 성립에 다툼이 없는 갑 제2호증 을 제5호증의 각 기재에 의하면 원고와 피고는 각자 자기채무의 이행을 제공한 바 없이 상대방의 채무이행만을 최고한 사실을 인정할 수 있으니 피고의 위 주장은 모두 그 이유없다 할 것이다.",
            "그렇다면 위 계약은 유효히 존속하고 있다 할 것이나 피고가 매매목적물인 위 부동산을 말경 타인에게 매도하여 그 사람에게 소유권이전등기를 경료한 사실은 피고 스스로 자인하는 바로서 특별한 사정이 없는 이 사건에 있어서 위 계약은 이행불능이라 할 것이므로 이를 이유로 이 소송에서 위 계약은 해제되었다 할 것이다.",
            "피고는 원고와 이사건 매매계약을 체결한 후 이를 믿고서 소외 3으로부터 부동산을 매수하여 매매대금을 지급하기로 약정한 바 있으나 원고의 채무불이행으로 피고는 위 소외인에게 중도금을 지급할 수 없어 위 소외인과의 계약금을 980000원을 반환받지 못하여 손해를 입었으므로 이의 배상을 구한다고 주장하나 이를 인정할 아무런 증거 없으니 위 피고의 주장은 이유없다.",
            "그렇다면 피고는 원고에게 위 계약금의 배액인 돈 1500000원 및 이에 대하여 원고가 구하는 바에 따라 이사건 소장부본송달 익일임이 기록상 명백한 19.부터 완제에 이르기까지 민법소정의 연 5푼의 율에 따른 지연손해금을 보태어 지급할 의무있다 할 것이므로 이를 구하는 원고의 이건 청구는 이유있어 이를 인용할 것인바 이와 결론을 달리한 원판결은 부당하여 이를 취소하고 소송 총비용에 관하여는 민사소송법 제96조 제95조 제89조를 가집행선고에 관하여는 같은법 제199조를 적용하여 주문과 같이 판결한다."
        ]
    },
    "close": {
        "cnclsns": [
            "원판결을 취소한다."
        ]
    }
}