{
    "info": {
        "caseField": "",
        "detailField": "",
        "trailField": "",
        "caseNm": "손해배상청구사건",
        "courtNm": "서울고법",
        "judmnAdjuDe": "1981.9.4.",
        "caseNo": "81나1311",
        "relateLaword": [],
        "qotatPrcdnt": []
    },
    "concerned": {
        "acusr": "",
        "dedat": ""
    },
    "org": {
        "orgJdgmnCourtNm": "",
        "orgJdgmnAdjuDe": "",
        "orgJdgmnCaseNo": ""
    },
    "disposal": {
        "disposalform": "",
        "disposalcontent": []
    },
    "mentionedItems": {
        "rqestObjet": []
    },
    "assrs": {
        "acusrAssrs": [],
        "dedatAssrs": []
    },
    "facts": {
        "bsisFacts": [
            "차량의 수리중 야기된 사고와 그 차량소유자의 책임 유무"
        ]
    },
    "dcss": {
        "courtDcss": [
            "원고들은 위 포니차는 피고의 차일 뿐만 아니라 피고가 위 차의 시동키를 위 수리공장에 넘겨주어 소외 2가 그 시동키로 시동을 걸어 위 차를 시운전하다가 이건 사고를 일으킨 것이니 동 소외인은 피고의 지시에 따라 시운전한 것으로 보아야 하고 따라서 피고는 자기를 위하여 위 포니차를 운행한 자로서 자동차손해배상보장법 제3조에 따라 이건 사고로 원고 1 및 그의 처 자 모인 나머지 원고들이 입게된 모든 손해를 배상할 책임이 있다고 주장하고 있다.",
            "살피건대 차의 소유자가 그 차의 수리를 위해 수리업자에게 이를 맡긴 때에는 그 차에 대한 운행의 지배는 수리업자에게로 넘어가 수리기간 중에는 의뢰자인 차주는 차의 취급에 개입할 수가 없는 것이므로 그 차에 대한 관리지배권은 없고 또 차의 수리에는 그 수리를 위해 필요한 운행과 시운전도 포함된다 할 것이므로 그 차가 시운전중 사고를 일으켰다면 차의 소유자로서는 그에 대한 책임이 없다고 봄이 상당하다 할 것이며 수리에 시운전이 포함된다고 보는 한 자동차의 소유자가 수리업자에게 시동키를 넘겨주는 것은 당연한 것으로서 달리 특별한 사정이 없는한 차주가 시동키를 수리업자에게 넘겨 주었다는 사실만으로는 그 차의 시운전이 차주의 구체적인 지시에 따른 것이었다고 보기는 어렵고 달리 이건 사고가 피고가 자기를 위하여 자동차를 운행중 일어난 사고였다고 인정할만한 주장입증이 없다.",
            "그렇다면 피고가 위 법 제3조의 자기를 위하여 자동차를 운행하는 자에 해당함을 전제하여 나아온 원고들의 이소청구는 나머지 점에 대한 판단에 나아갈 것 없이 벌써 이유없음이 명백하므로 이를 모두 기각하여야 할 것인바 이와 결론을 같이한 원판결은 정당하고 원고들의 항소는 이유없으므로 이를 모두 기각하며 항소비용은 패소자인 원고들의 부담으로 하여 주문과 같이 판결한다."
        ]
    },
    "close": {
        "cnclsns": [
            "원고들의 항소를 모두 기각한다."
        ]
    }
}