{
    "info": {
        "caseField": "",
        "detailField": "",
        "trailField": "",
        "caseNm": "경작권확인",
        "courtNm": "대법원",
        "judmnAdjuDe": "1955.1.30.",
        "caseNo": "4287민상190",
        "relateLaword": [],
        "qotatPrcdnt": []
    },
    "concerned": {
        "acusr": "",
        "dedat": ""
    },
    "org": {
        "orgJdgmnCourtNm": "",
        "orgJdgmnAdjuDe": "",
        "orgJdgmnCaseNo": ""
    },
    "disposal": {
        "disposalform": "",
        "disposalcontent": []
    },
    "mentionedItems": {
        "rqestObjet": []
    },
    "assrs": {
        "acusrAssrs": [],
        "dedatAssrs": []
    },
    "facts": {
        "bsisFacts": [
            "농지에 관한 공부상 허위기재와 농지개혁법 의 규정에 의한 소송의 적부"
        ]
    },
    "dcss": {
        "courtDcss": [
            "심안하니 기록에 의하여 제1심 이래 원고의 변론의 취지를 종합하면 원판결기재와 동일함을 간취할 수 그리고 본건에 있어 본건 토지가 농지개혁법에 의하여 원고가 분배를 받은 농지라고 주장하고 피고의 자작자로 인정한 관의 처사가 부당하다는 것이면 동 조치에 대한 동 농지개혁법에 의한 이의를 거친 후가 아니면 본소를 제기할 수 없는 것이나 본소에 있어서는 그렇지 않고 피고가 정당히 자작지로 인정을 받은 것이 아니고 공문서를 위조하여 공부상에 이를 피고의 자작지로 허위기재케 하였다는 것이므로 이를 농지개혁법제24조에 의한 소송이라 할 수 없고 이의의 여부를 논할 바 여하간 원고는 그 주장에 관한 공문서의 위조 급 허위기재사실을 입증할 책임이 있는 바 원고 제출의 갑 각호증이 우 사실을 증명할 자료가 되지 못할 것이 기록상 명백함으로 원심이 갑호증에 대한 판단을 하지 않고 원고의 주장사실을 증명할 재료가 없다하여 원고의 청구를 배척한 것은 정당하고 소호의 위법이 없으며 그리고 원고가 분배를 받지 않은 이상 피고에 대하여 경작권을주장할 수도 없는 따라서 논지 이유없고 본건 상고 이유없음이 명백함으로 민사소송법 제401조 제89조 제95조를 적용하여 주문과 같이 판결한 것이다."
        ]
    },
    "close": {
        "cnclsns": [
            "본건상고를 기각한다."
        ]
    }
}