{
    "info": {
        "caseField": "",
        "detailField": "",
        "trailField": "",
        "caseNm": "허위공문서작성,허위공문서작성행사,사문서위조,사문서위조행사",
        "courtNm": "대법원",
        "judmnAdjuDe": "1971.8.31.",
        "caseNo": "71도1052",
        "relateLaword": [],
        "qotatPrcdnt": []
    },
    "concerned": {
        "acusr": "",
        "dedat": ""
    },
    "org": {
        "orgJdgmnCourtNm": "",
        "orgJdgmnAdjuDe": "",
        "orgJdgmnCaseNo": ""
    },
    "disposal": {
        "disposalform": "",
        "disposalcontent": []
    },
    "mentionedItems": {
        "rqestObjet": []
    },
    "assrs": {
        "acusrAssrs": [],
        "dedatAssrs": []
    },
    "facts": {
        "bsisFacts": [
            "이장이 직무에 관하여 작성하는 문서는 공문서이다."
        ]
    },
    "dcss": {
        "courtDcss": [
            "직권으로 판단하건대 원판결이 인용한 1심판결은 피고인이 수해복구를 위한 중장기성자금 융자대상자 변경통보서에 전남 영광군 ○○면 △△리 이장 공소외 1과 같은 면 □□리 이장 공소외 2의 승낙없이 그 정을 모르는 같은 면사무소 임시직원 공소외 3으로 하여금 위 각 이장 명의의 공소외 4 및 공소외 5에 대한 수해보고서를 작성케 하고 그 인장을 임의로 각 조각하여 위 문서에 각각 날인하여 위조 행사한 사실을 인정한후 이를 사문서위조 동행사로 판단하였다.",
            "그러나 이장도 지방자치법 제146조 지방자치에관한임시특별조치법 제9조의 3에서 규정하고 있는 지방자치단체의 기관으로서 그가 직무에 관하여 작성하는 문서는 공문서이지 사문서가 아님에도 불구하고 위 문서의 위조 및 동행사를 사문서 위조 및 동행사로 판단한 1심판결을 인용한 원판결에는 법령오해의 위법이 있다할 것이므로 원판결은 파기를 면치 못할 것이다.",
            "따라서 형사소송법 제397조에 의하여 관여법관의 일치된 의견으로 주문과 같이 판결한다."
        ]
    },
    "close": {
        "cnclsns": [
            "원판결을 파기하고 사건을 광주지방법원 합의부에 환송한다."
        ]
    }
}